{
    "animalcrossingamiibos": {
        "ban": {
            "compromised": [],
            "scammer": [],
            "sketchy": [],
            "troll": []
        },
        "unban": {
            "scammer": [],
            "sketchy": []
        }
    },
    "dogemarket": {
        "ban": {
            "compromised": [],
            "scammer": [],
            "sketchy": [],
            "troll": []
        },
        "unban": {
            "scammer": [],
            "sketchy": []
        }
    },
    "funkoppopmod": {
        "ban": {
            "compromised": [],
            "scammer": [],
            "sketchy": [],
            "troll": []
        },
        "unban": {
            "scammer": [],
            "sketchy": []
        }
    },
    "funkoswap": {
        "ban": {
            "scammer": [],
            "sketchy": []
        },
        "unban": {
            "scammer": [
                "test2"
            ],
            "sketchy": []
        }
    },
    "gctrading": {
        "ban": {
            "compromised": [],
            "scammer": [],
            "sketchy": [],
            "troll": []
        },
        "unban": {
            "scammer": [],
            "sketchy": []
        }
    },
    "hockeyjerseys": {
        "ban": {
            "compromised": [],
            "scammer": [],
            "sketchy": [],
            "troll": []
        },
        "unban": {
            "scammer": []
        }
    },
    "mangaswap": {
        "ban": {
            "scammer": []
        },
        "unban": {}
    },
    "shave_bazaar": {
        "ban": {
            "compromised": [],
            "scammer": [],
            "sketchy": [],
            "troll": []
        },
        "unban": {
            "scammer": [
                "test2"
            ],
            "sketchy": []
        }
    },
    "ulgeartrade": {
        "ban": {
            "compromised": [],
            "scammer": [],
            "sketchy": [],
            "troll": []
        },
        "unban": {
            "scammer": []
        }
    }
}