{
    "airsoftmarket": 1709748283.0,
    "airsoftmarketcanada": 1709748230.0,
    "appleswap": 1722323918.0,
    "assistance": 1722326175.0,
    "avatartrading": 1722323974.0,
    "avexchange": 1722323919.0,
    "borrow": 1722325662.0,
    "canadianhardwareswap": 1722323986.0,
    "canadianknifeswap": 1722323935.0,
    "care": 1722324115.0,
    "cash4cash": 1722324347.0,
    "charity": 1722323941.0,
    "comicswap": 1722326459.0,
    "digitalcodesell": 1722323991.0,
    "discexchange": 1710432897.0,
    "disneypinswap": 1722323948.0,
    "donedirtcheap": 1722323948.0,
    "edcexchange": 1722326445.0,
    "food_pantry": 1722323974.0,
    "forhire": 1722326251.0,
    "funkoppopmod": 1711740423.0,
    "funkoswap": 1722323943.0,
    "gamesale": 1722325392.0,
    "gameswap": 1722323968.0,
    "gametrade": 1722323875.0,
    "garlicmarket": 1705885027.0,
    "gctrading": 1697857536.0,
    "gctrep": 1699292855.0,
    "gcxrep": 1687145095.0,
    "geartrade": 1722326485.0,
    "giftcardexchange": 1722326597.0,
    "giftofgames": 1722326331.0,
    "gofundme": 1722326021.0,
    "gunaccessoriesforsale": 1722326560.0,
    "hardwareswap": 1722323925.0,
    "hardwareswapuk": 1722325896.0,
    "hireagirlfriend": 1722326497.0,
    "hireawriter": 1722326199.0,
    "hockeyjerseys": 1722323958.0,
    "hutcoinsales": 1700590227.0,
    "igsrep": 1711733155.0,
    "indiegameswap": 1722323952.0,
    "knife_swap": 1722326515.0,
    "legomarket": 1722323971.0,
    "lolboosting": 1722323949.0,
    "machinedpens": 1722323957.0,
    "mangaswap": 1722325431.0,
    "mcsplaystation": 1687271681.0,
    "mcsrep": 1687271681.0,
    "mcsxbox": 1687272519.0,
    "mechmarket": 1722326412.0,
    "miniswap": 1722323977.0,
    "mousemarket": 1722324693.0,
    "nba2kmtselling": 1700590185.0,
    "nbarep": 1700590190.0,
    "need": 1722323935.0,
    "overwatchboosting": 1722323967.0,
    "pen_swap": 1722323938.0,
    "phoneverification": 1722323931.0,
    "photomarket": 1722326443.0,
    "playingcardsmarket": 1722323935.0,
    "pmsforsale": 1722324754.0,
    "random_acts_of_amazon": 1722323941.0,
    "random_acts_of_pizza": 1722326077.0,
    "randomactsofchristmas": 1722323957.0,
    "randomactsofpetfood": 1722323935.0,
    "randomactsoftacobell": 1722323958.0,
    "randomkindness": 1722323976.0,
    "referral": 1722326048.0,
    "referrals": 1722323953.0,
    "retrogameswap": 1722323972.0,
    "rocketleagueexchange": 1703789740.0,
    "sgsflair": 1711733194.0,
    "shave_bazaar": 1722325798.0,
    "signupsforpay": 1722326403.0,
    "slavelabour": 1722325004.0,
    "snackexchange": 1722326464.0,
    "starcitizen_trades": 1722325071.0,
    "steamgameswap": 1722323927.0,
    "thinkpadsforsale": 1722323943.0,
    "trade": 1686162219.0,
    "ulgeartrade": 1722323973.0,
    "universalscammerlist": 1722324109.0,
    "uvtrade": 1722326431.0,
    "vinylcollectors": 1722326579.0,
    "watchexchange": 1722326405.0,
    "watchexchangecanada": 1722323963.0,
    "ygomarketplace": 1710233300.0
}