{
    "airsoftmarket": 1709748283.0,
    "airsoftmarketcanada": 1709748230.0,
    "appleswap": 1717311212.0,
    "assistance": 1717315238.0,
    "avatartrading": 1717303543.0,
    "avexchange": 1717307091.0,
    "borrow": 1717315069.0,
    "canadianhardwareswap": 1717304162.0,
    "canadianknifeswap": 1717299557.0,
    "care": 1717301554.0,
    "cash4cash": 1717311698.0,
    "charity": 1717305929.0,
    "comicswap": 1717299591.0,
    "digitalcodesell": 1717307370.0,
    "discexchange": 1710432897.0,
    "disneypinswap": 1717306477.0,
    "donedirtcheap": 1717312546.0,
    "edcexchange": 1717311944.0,
    "food_pantry": 1717301522.0,
    "forhire": 1717314200.0,
    "funkoppopmod": 1711740423.0,
    "funkoswap": 1717310384.0,
    "gamesale": 1717310406.0,
    "gameswap": 1717306717.0,
    "gametrade": 1717299544.0,
    "garlicmarket": 1705885027.0,
    "gctrading": 1697857536.0,
    "gctrep": 1699292855.0,
    "gcxrep": 1687145095.0,
    "geartrade": 1717315305.0,
    "giftcardexchange": 1717315213.0,
    "giftofgames": 1717315372.0,
    "gofundme": 1717314486.0,
    "gunaccessoriesforsale": 1717314954.0,
    "hardwareswap": 1717314456.0,
    "hardwareswapuk": 1717299606.0,
    "hireagirlfriend": 1717305899.0,
    "hireawriter": 1717299558.0,
    "hockeyjerseys": 1717315385.0,
    "hutcoinsales": 1700590227.0,
    "igsrep": 1711733155.0,
    "indiegameswap": 1717299555.0,
    "knife_swap": 1717315268.0,
    "legomarket": 1717315383.0,
    "lolboosting": 1717315427.0,
    "machinedpens": 1717299575.0,
    "mangaswap": 1717315371.0,
    "mcsplaystation": 1687271681.0,
    "mcsrep": 1687271681.0,
    "mcsxbox": 1687272519.0,
    "mechmarket": 1717314125.0,
    "miniswap": 1717312598.0,
    "mousemarket": 1717315085.0,
    "nba2kmtselling": 1700590185.0,
    "nbarep": 1700590190.0,
    "need": 1717301583.0,
    "overwatchboosting": 1717299599.0,
    "pen_swap": 1717309487.0,
    "phoneverification": 1717301518.0,
    "photomarket": 1717313348.0,
    "playingcardsmarket": 1717299549.0,
    "pmsforsale": 1717315351.0,
    "random_acts_of_amazon": 1717315394.0,
    "random_acts_of_pizza": 1717309961.0,
    "randomactsofchristmas": 1717299612.0,
    "randomactsofpetfood": 1717301542.0,
    "randomactsoftacobell": 1717307720.0,
    "randomkindness": 1717301589.0,
    "referral": 1717311119.0,
    "referrals": 1717314727.0,
    "retrogameswap": 1717301553.0,
    "rocketleagueexchange": 1703789740.0,
    "sgsflair": 1711733194.0,
    "shave_bazaar": 1717299598.0,
    "signupsforpay": 1717315047.0,
    "slavelabour": 1717315041.0,
    "snackexchange": 1717301551.0,
    "starcitizen_trades": 1717314713.0,
    "steamgameswap": 1717314045.0,
    "thinkpadsforsale": 1717299556.0,
    "trade": 1686162219.0,
    "ulgeartrade": 1717310396.0,
    "universalscammerlist": 1717301591.0,
    "uvtrade": 1717307258.0,
    "vinylcollectors": 1717315398.0,
    "watchexchange": 1717315261.0,
    "watchexchangecanada": 1717312774.0,
    "ygomarketplace": 1710233300.0
}