{
    "airsoftmarket": 1675065521.0,
    "airsoftmarketcanada": 1675059761.0,
    "appleswap": 1675063512.0,
    "assistance": 1675065611.0,
    "avexchange": 1675065734.0,
    "borrow": 1675064958.0,
    "canadianhardwareswap": 1675059782.0,
    "care": 1675064915.0,
    "cash4cash": 1675064556.0,
    "charity": 1675064912.0,
    "comicswap": 1675052136.0,
    "digitalcodesell": 1675065653.0,
    "disneypinswap": 1675052137.0,
    "food_pantry": 1675064912.0,
    "forhire": 1675065672.0,
    "funkoppopmod": 1675052130.0,
    "funkoswap": 1675063105.0,
    "gamesale": 1674963277.0,
    "gameswap": 1674963331.0,
    "gametrade": 1675052135.0,
    "garlicmarket": 1675052135.0,
    "gctrading": 1675063695.0,
    "gctrep": 1675052134.0,
    "gcxrep": 1675052127.0,
    "giftcardexchange": 1675063903.0,
    "giftofgames": 1675065809.0,
    "gofundme": 1675064912.0,
    "gunaccessoriesforsale": 1675064345.0,
    "hardwareswapuk": 1675052128.0,
    "hutcoinsales": 1675052126.0,
    "igsrep": 1675052129.0,
    "indiegameswap": 1675052137.0,
    "knife_swap": 1675065056.0,
    "legomarket": 1675059915.0,
    "lolboosting": 1675052134.0,
    "mangaswap": 1675065682.0,
    "mcsplaystation": 1675060228.0,
    "mcsrep": 1675059114.0,
    "mcsxbox": 1675059869.0,
    "mechmarket": 1675065814.0,
    "miniswap": 1675059993.0,
    "mousemarket": 1675063525.0,
    "nba2kmtselling": 1675052082.0,
    "nbarep": 1675052137.0,
    "need": 1675064914.0,
    "overwatchboosting": 1675052128.0,
    "pen_swap": 1675063831.0,
    "photomarket": 1675060288.0,
    "playingcardsmarket": 1675052100.0,
    "pmsforsale": 1675056538.0,
    "random_acts_of_amazon": 1675064196.0,
    "random_acts_of_pizza": 1675064890.0,
    "randomactsofchristmas": 1675052134.0,
    "randomactsofpetfood": 1675064913.0,
    "randomkindness": 1675064913.0,
    "rocketleagueexchange": 1675065246.0,
    "sgsflair": 1675052123.0,
    "signupsforpay": 1675062184.0,
    "slavelabour": 1675065506.0,
    "snackexchange": 1675061791.0,
    "starcitizen_trades": 1675065013.0,
    "steamgameswap": 1675062438.0,
    "thinkpadsforsale": 1675063716.0,
    "trade": 1675052135.0,
    "universalscammerlist": 1675064930.0,
    "uvtrade": 1675065652.0,
    "vinylcollectors": 1675065781.0,
    "watchexchange": 1675065810.0
}