{
    "airsoftmarket": 1688629003.0,
    "airsoftmarketcanada": 1688629002.0,
    "appleswap": 1688629779.0,
    "assistance": 1688630290.0,
    "avatartrading": 1688630409.0,
    "avexchange": 1688630442.0,
    "borrow": 1688630512.0,
    "canadianhardwareswap": 1688628999.0,
    "canadianknifeswap": 1688629001.0,
    "care": 1688629004.0,
    "cash4cash": 1688629086.0,
    "charity": 1688629004.0,
    "comicswap": 1688629003.0,
    "digitalcodesell": 1688630596.0,
    "discexchange": 1688628996.0,
    "disneypinswap": 1688629003.0,
    "edcexchange": 1688630445.0,
    "food_pantry": 1688628995.0,
    "forhire": 1688630223.0,
    "funkoppopmod": 1683062566.0,
    "funkoswap": 1688629004.0,
    "gamesale": 1688629001.0,
    "gameswap": 1688629001.0,
    "gametrade": 1688629004.0,
    "garlicmarket": 1688629003.0,
    "gctrading": 1688629003.0,
    "gctrep": 1688629002.0,
    "gcxrep": 1687145095.0,
    "geartrade": 1688630453.0,
    "giftcardexchange": 1687167571.0,
    "giftofgames": 1688630608.0,
    "gofundme": 1688630001.0,
    "gunaccessoriesforsale": 1688629886.0,
    "hardwareswapuk": 1688629001.0,
    "hockeyjerseys": 1688629001.0,
    "hutcoinsales": 1688629000.0,
    "igsrep": 1688629002.0,
    "indiegameswap": 1688629004.0,
    "knife_swap": 1688630567.0,
    "legomarket": 1688629005.0,
    "lolboosting": 1688630581.0,
    "mangaswap": 1688630467.0,
    "mcsplaystation": 1687271681.0,
    "mcsrep": 1687271681.0,
    "mcsxbox": 1687272519.0,
    "mechmarket": 1688629005.0,
    "miniswap": 1688630494.0,
    "mousemarket": 1688629003.0,
    "nba2kmtselling": 1688629000.0,
    "nbarep": 1688629003.0,
    "need": 1688628998.0,
    "overwatchboosting": 1688629004.0,
    "pen_swap": 1688630424.0,
    "photomarket": 1688629004.0,
    "playingcardsmarket": 1688628989.0,
    "pmsforsale": 1688630561.0,
    "random_acts_of_amazon": 1688629002.0,
    "random_acts_of_pizza": 1688629003.0,
    "randomactsofchristmas": 1688629004.0,
    "randomactsofpetfood": 1688628996.0,
    "randomactsoftacobell": 1688628987.0,
    "randomkindness": 1688629004.0,
    "retrogameswap": 1688629001.0,
    "rocketleagueexchange": 1688629194.0,
    "sgsflair": 1688629004.0,
    "shave_bazaar": 1688629004.0,
    "signupsforpay": 1688629515.0,
    "slavelabour": 1688629723.0,
    "snackexchange": 1688629004.0,
    "starcitizen_trades": 1688629936.0,
    "steamgameswap": 1688629004.0,
    "thinkpadsforsale": 1688629005.0,
    "trade": 1686162219.0,
    "ulgeartrade": 1688630305.0,
    "universalscammerlist": 1688629005.0,
    "uvtrade": 1688630562.0,
    "vinylcollectors": 1688630566.0,
    "watchexchange": 1688629472.0,
    "watchexchangecanada": 1688628989.0,
    "ygomarketplace": 1688628989.0
}